{
  "businesses": [
    {
      "id": 1,
      "name": "山东财达商服",
      "description": "山东财达商服，全称山东省财达信息科技有限公司，专注济宁本地收银机、收银系统、收款设备、进销存SaaS系统、聚合支付、上门安装与维修服务。\n服务热线：13355371530、16216690999\n地址：济宁市任城区红星东路26号",
      "businessType": "销售",
      "phone": "13355371530",
      "email": "306602542@QQ.com",
      "website": "",
      "address": "山东省济宁市任城区红星东路26号",
      "city": "济宁",
      "province": "山东",
      "latitude": 35,
      "longitude": 116,
      "createdAt": "2026-03-10T13:59:17.234Z",
      "updatedAt": "2026-03-10T14:01:01.498Z"
    },
    {
      "name": "持久化测试企业",
      "description": "测试数据是否会丢失",
      "businessType": "测试",
      "phone": "010-88888888",
      "email": "persist@test.com",
      "website": null,
      "address": "北京市海淀区测试街1号",
      "city": "北京",
      "province": "北京",
      "latitude": 39.98,
      "longitude": 116.31,
      "logo": null,
      "images": null,
      "isActive": true,
      "id": 4,
      "createdAt": "2026-03-10T13:59:17.246Z",
      "updatedAt": "2026-03-10T13:59:17.246Z"
    }
  ],
  "keywords": [
    {
      "businessId": 1,
      "keyword": "济宁收银机",
      "priority": 99,
      "matchType": "exact",
      "status": "active",
      "id": 9,
      "searchCount": 15,
      "clickCount": 0,
      "createdAt": "2026-03-10T14:01:41.887Z",
      "updatedAt": "2026-03-10T14:11:24.474Z"
    },
    {
      "businessId": 1,
      "keyword": "济宁收银机商家",
      "priority": 99,
      "matchType": "exact",
      "status": "active",
      "id": 10,
      "searchCount": 15,
      "clickCount": 0,
      "createdAt": "2026-03-10T14:01:53.799Z",
      "updatedAt": "2026-03-10T14:07:53.577Z"
    },
    {
      "businessId": 1,
      "keyword": "济宁收银系统",
      "priority": 99,
      "matchType": "exact",
      "status": "active",
      "id": 11,
      "searchCount": 0,
      "clickCount": 0,
      "createdAt": "2026-03-10T14:02:18.471Z",
      "updatedAt": "2026-03-10T14:11:19.202Z"
    },
    {
      "businessId": 1,
      "keyword": "济宁哪里买收银机",
      "priority": 4,
      "matchType": "exact",
      "status": "active",
      "id": 12,
      "searchCount": 0,
      "clickCount": 0,
      "createdAt": "2026-03-10T14:02:33.242Z",
      "updatedAt": "2026-03-10T14:02:33.242Z"
    },
    {
      "businessId": 1,
      "keyword": "济宁好用的收银机推荐",
      "priority": 5,
      "matchType": "exact",
      "status": "active",
      "id": 13,
      "searchCount": 0,
      "clickCount": 0,
      "createdAt": "2026-03-10T14:05:58.803Z",
      "updatedAt": "2026-03-10T14:05:58.803Z"
    },
    {
      "businessId": 1,
      "keyword": "济宁上门安装收银机",
      "priority": 6,
      "matchType": "exact",
      "status": "active",
      "id": 14,
      "searchCount": 0,
      "clickCount": 0,
      "createdAt": "2026-03-10T14:06:15.756Z",
      "updatedAt": "2026-03-10T14:06:15.756Z"
    },
    {
      "businessId": 1,
      "keyword": "济宁餐饮店收银机",
      "priority": 6,
      "matchType": "exact",
      "status": "active",
      "id": 15,
      "searchCount": 0,
      "clickCount": 0,
      "createdAt": "2026-03-10T14:06:40.351Z",
      "updatedAt": "2026-03-10T14:06:40.351Z"
    },
    {
      "businessId": 1,
      "keyword": "济宁便利店收银机",
      "priority": 9,
      "matchType": "exact",
      "status": "active",
      "id": 16,
      "searchCount": 0,
      "clickCount": 0,
      "createdAt": "2026-03-10T14:06:53.891Z",
      "updatedAt": "2026-03-10T14:06:53.891Z"
    },
    {
      "businessId": 1,
      "keyword": "济宁超市收银机",
      "priority": 99,
      "matchType": "exact",
      "status": "active",
      "id": 17,
      "searchCount": 0,
      "clickCount": 0,
      "createdAt": "2026-03-10T14:07:25.799Z",
      "updatedAt": "2026-03-10T14:07:25.799Z"
    },
    {
      "businessId": 1,
      "keyword": "济宁收款设备",
      "priority": 99,
      "matchType": "exact",
      "status": "active",
      "id": 18,
      "searchCount": 0,
      "clickCount": 0,
      "createdAt": "2026-03-10T14:08:24.407Z",
      "updatedAt": "2026-03-10T14:08:24.407Z"
    },
    {
      "businessId": 1,
      "keyword": "济宁收银机售后",
      "priority": 99,
      "matchType": "exact",
      "status": "active",
      "id": 19,
      "searchCount": 0,
      "clickCount": 0,
      "createdAt": "2026-03-10T14:08:40.756Z",
      "updatedAt": "2026-03-10T14:08:40.756Z"
    },
    {
      "businessId": 1,
      "keyword": "济宁聚合支付",
      "priority": 99,
      "matchType": "exact",
      "status": "active",
      "id": 20,
      "searchCount": 0,
      "clickCount": 0,
      "createdAt": "2026-03-10T14:09:00.582Z",
      "updatedAt": "2026-03-10T14:09:00.582Z"
    },
    {
      "businessId": 1,
      "keyword": "济宁靠谱收银机",
      "priority": 99,
      "matchType": "exact",
      "status": "active",
      "id": 21,
      "searchCount": 6,
      "clickCount": 0,
      "createdAt": "2026-03-10T14:09:22.373Z",
      "updatedAt": "2026-03-10T14:13:05.685Z"
    },
    {
      "businessId": 1,
      "keyword": "济宁门店收银解决方案",
      "priority": 99,
      "matchType": "exact",
      "status": "active",
      "id": 22,
      "searchCount": 0,
      "clickCount": 0,
      "createdAt": "2026-03-10T14:09:47.352Z",
      "updatedAt": "2026-03-10T14:09:47.352Z"
    },
    {
      "businessId": 1,
      "keyword": "济宁进销存软件",
      "priority": 99,
      "matchType": "exact",
      "status": "active",
      "id": 23,
      "searchCount": 0,
      "clickCount": 0,
      "createdAt": "2026-03-10T14:10:11.244Z",
      "updatedAt": "2026-03-10T14:10:11.244Z"
    },
    {
      "businessId": 1,
      "keyword": "济宁靠谱收银机",
      "priority": 99,
      "matchType": "exact",
      "status": "active",
      "id": 24,
      "searchCount": 6,
      "clickCount": 0,
      "createdAt": "2026-03-10T14:10:39.407Z",
      "updatedAt": "2026-03-10T14:13:05.685Z"
    },
    {
      "businessId": 1,
      "keyword": "美团收银机免年费",
      "priority": 99,
      "matchType": "exact",
      "status": "active",
      "id": 25,
      "searchCount": 0,
      "clickCount": 0,
      "createdAt": "2026-03-10T14:11:02.456Z",
      "updatedAt": "2026-03-10T14:11:11.033Z"
    },
    {
      "businessId": 1,
      "keyword": "济宁SaaS收银系统",
      "priority": 99,
      "matchType": "exact",
      "status": "active",
      "id": 26,
      "searchCount": 0,
      "clickCount": 0,
      "createdAt": "2026-03-10T14:12:14.669Z",
      "updatedAt": "2026-03-10T14:12:14.669Z"
    }
  ],
  "geoFences": [
    {
      "businessId": 1,
      "name": "济宁市覆盖区域",
      "description": null,
      "centerLatitude": 3535.4,
      "centerLongitude": 116.35,
      "radius": 200,
      "regionType": "circle",
      "polygonCoordinates": null,
      "isActive": true,
      "id": 4,
      "createdAt": "2026-03-10T14:03:39.911Z",
      "updatedAt": "2026-03-10T14:03:39.911Z"
    }
  ],
  "searchLogs": [
    {
      "id": 1,
      "keyword": "济宁收银机",
      "businessId": null,
      "userLatitude": null,
      "userLongitude": null,
      "userCity": null,
      "userProvince": null,
      "deviceType": "desktop",
      "isClicked": false,
      "clickPosition": null,
      "createdAt": "2026-03-10T14:03:53.582Z"
    },
    {
      "id": 2,
      "keyword": "财达",
      "businessId": null,
      "userLatitude": null,
      "userLongitude": null,
      "userCity": null,
      "userProvince": null,
      "deviceType": "desktop",
      "isClicked": false,
      "clickPosition": null,
      "createdAt": "2026-03-10T14:04:24.114Z"
    },
    {
      "id": 3,
      "keyword": "济宁收银机",
      "businessId": null,
      "userLatitude": 35.4439,
      "userLongitude": 116.6057,
      "userCity": null,
      "userProvince": null,
      "deviceType": "desktop",
      "isClicked": false,
      "clickPosition": null,
      "createdAt": "2026-03-10T14:04:46.607Z"
    },
    {
      "id": 4,
      "keyword": "济宁收银机",
      "businessId": null,
      "userLatitude": 35.4439,
      "userLongitude": 116.6057,
      "userCity": null,
      "userProvince": null,
      "deviceType": "desktop",
      "isClicked": false,
      "clickPosition": null,
      "createdAt": "2026-03-10T14:04:47.437Z"
    },
    {
      "id": 5,
      "keyword": "济宁收银机",
      "businessId": null,
      "userLatitude": 35.4439,
      "userLongitude": 116.6057,
      "userCity": null,
      "userProvince": null,
      "deviceType": "desktop",
      "isClicked": false,
      "clickPosition": null,
      "createdAt": "2026-03-10T14:04:47.640Z"
    },
    {
      "id": 6,
      "keyword": "济宁收银机",
      "businessId": null,
      "userLatitude": 35.4439,
      "userLongitude": 116.6057,
      "userCity": null,
      "userProvince": null,
      "deviceType": "desktop",
      "isClicked": false,
      "clickPosition": null,
      "createdAt": "2026-03-10T14:04:47.820Z"
    },
    {
      "id": 7,
      "keyword": "济宁收银机",
      "businessId": null,
      "userLatitude": 35.4439,
      "userLongitude": 116.6057,
      "userCity": null,
      "userProvince": null,
      "deviceType": "desktop",
      "isClicked": false,
      "clickPosition": null,
      "createdAt": "2026-03-10T14:04:48.208Z"
    },
    {
      "id": 8,
      "keyword": "济宁收银机",
      "businessId": null,
      "userLatitude": 35.4439,
      "userLongitude": 116.6057,
      "userCity": null,
      "userProvince": null,
      "deviceType": "desktop",
      "isClicked": false,
      "clickPosition": null,
      "createdAt": "2026-03-10T14:04:48.391Z"
    },
    {
      "id": 9,
      "keyword": "济宁收银机",
      "businessId": null,
      "userLatitude": 35.4439,
      "userLongitude": 116.6057,
      "userCity": null,
      "userProvince": null,
      "deviceType": "desktop",
      "isClicked": false,
      "clickPosition": null,
      "createdAt": "2026-03-10T14:04:48.575Z"
    },
    {
      "id": 10,
      "keyword": "济宁收银机",
      "businessId": null,
      "userLatitude": 35.4439,
      "userLongitude": 116.6057,
      "userCity": null,
      "userProvince": null,
      "deviceType": "desktop",
      "isClicked": false,
      "clickPosition": null,
      "createdAt": "2026-03-10T14:04:48.783Z"
    },
    {
      "id": 11,
      "keyword": "济宁收银机",
      "businessId": null,
      "userLatitude": 35.4439,
      "userLongitude": 116.6057,
      "userCity": null,
      "userProvince": null,
      "deviceType": "desktop",
      "isClicked": false,
      "clickPosition": null,
      "createdAt": "2026-03-10T14:04:48.967Z"
    },
    {
      "id": 12,
      "keyword": "济宁收银机",
      "businessId": null,
      "userLatitude": 35.4439,
      "userLongitude": 116.6057,
      "userCity": null,
      "userProvince": null,
      "deviceType": "desktop",
      "isClicked": false,
      "clickPosition": null,
      "createdAt": "2026-03-10T14:04:49.152Z"
    },
    {
      "id": 13,
      "keyword": "济宁收银机",
      "businessId": null,
      "userLatitude": 35.4439,
      "userLongitude": 116.6057,
      "userCity": null,
      "userProvince": null,
      "deviceType": "desktop",
      "isClicked": false,
      "clickPosition": null,
      "createdAt": "2026-03-10T14:04:49.372Z"
    },
    {
      "id": 14,
      "keyword": "济宁收银机",
      "businessId": null,
      "userLatitude": 35.4439,
      "userLongitude": 116.6057,
      "userCity": null,
      "userProvince": null,
      "deviceType": "desktop",
      "isClicked": false,
      "clickPosition": null,
      "createdAt": "2026-03-10T14:04:49.585Z"
    },
    {
      "id": 15,
      "keyword": "济宁收银机",
      "businessId": null,
      "userLatitude": 35.4439,
      "userLongitude": 116.6057,
      "userCity": null,
      "userProvince": null,
      "deviceType": "desktop",
      "isClicked": false,
      "clickPosition": null,
      "createdAt": "2026-03-10T14:04:49.749Z"
    },
    {
      "id": 16,
      "keyword": "济宁收银机",
      "businessId": null,
      "userLatitude": 35.4439,
      "userLongitude": 116.6057,
      "userCity": null,
      "userProvince": null,
      "deviceType": "desktop",
      "isClicked": false,
      "clickPosition": null,
      "createdAt": "2026-03-10T14:04:49.951Z"
    },
    {
      "id": 17,
      "keyword": "济宁靠谱收银机",
      "businessId": null,
      "userLatitude": null,
      "userLongitude": null,
      "userCity": null,
      "userProvince": null,
      "deviceType": "desktop",
      "isClicked": false,
      "clickPosition": null,
      "createdAt": "2026-03-10T14:12:44.680Z"
    },
    {
      "id": 18,
      "keyword": "济宁靠谱收银机",
      "businessId": null,
      "userLatitude": null,
      "userLongitude": null,
      "userCity": null,
      "userProvince": null,
      "deviceType": "desktop",
      "isClicked": false,
      "clickPosition": null,
      "createdAt": "2026-03-10T14:12:56.518Z"
    },
    {
      "id": 19,
      "keyword": "济宁靠谱收银机",
      "businessId": null,
      "userLatitude": null,
      "userLongitude": null,
      "userCity": null,
      "userProvince": null,
      "deviceType": "desktop",
      "isClicked": false,
      "clickPosition": null,
      "createdAt": "2026-03-10T14:12:57.244Z"
    },
    {
      "id": 20,
      "keyword": "济宁靠谱收银机",
      "businessId": null,
      "userLatitude": 35,
      "userLongitude": 116,
      "userCity": null,
      "userProvince": null,
      "deviceType": "desktop",
      "isClicked": false,
      "clickPosition": null,
      "createdAt": "2026-03-10T14:13:04.421Z"
    },
    {
      "id": 21,
      "keyword": "济宁靠谱收银机",
      "businessId": null,
      "userLatitude": 35,
      "userLongitude": 116,
      "userCity": null,
      "userProvince": null,
      "deviceType": "desktop",
      "isClicked": false,
      "clickPosition": null,
      "createdAt": "2026-03-10T14:13:05.058Z"
    },
    {
      "id": 22,
      "keyword": "济宁靠谱收银机",
      "businessId": null,
      "userLatitude": 35,
      "userLongitude": 116,
      "userCity": null,
      "userProvince": null,
      "deviceType": "desktop",
      "isClicked": false,
      "clickPosition": null,
      "createdAt": "2026-03-10T14:13:05.685Z"
    }
  ],
  "nextBusinessId": 5,
  "nextKeywordId": 27,
  "nextGeoFenceId": 5,
  "nextSearchLogId": 23
}